avst/__init__.py
avst/cut.py
avst/io.py
avst/sync.py
avst/sync_algorithm.py
avst-1.1.1.dist-info/METADATA
avst-1.1.1.dist-info/WHEEL
avst-1.1.1.dist-info/entry_points.txt
avst-1.1.1.dist-info/licenses/LICENSE
avst-1.1.1.dist-info/RECORD
