Metadata-Version: 2.4
Name: avst
Version: 1.1.1
Summary: Audio Video Sync Tool
Project-URL: Documentation, https://github.com/fodorad/avst#readme
Project-URL: Issues, https://github.com/fodorad/avst/issues
Project-URL: Source, https://github.com/fodorad/avst
Author-email: fodorad <fodorad201@gmail.com>
License-File: LICENSE
Keywords: audio,sync,video
Classifier: Operating System :: OS Independent
Classifier: Programming Language :: Python :: 3
Requires-Python: >=3.11
Requires-Dist: opencv-python
Requires-Dist: scipy
Requires-Dist: soundfile
Requires-Dist: tqdm
